[
    { "constituency": "Belfast East", "name": "Robinson, P.*", "party": "DUP", "votes": 15152, "percentage": 0.491, "change": "+", "changeAmount": 6.6   },
    { "constituency": "Belfast East", "name": "Empey, R.", "party": "UU", "votes": 9275, "percentage": 0.301, "change": "+", "changeAmount": 6.9   },
    { "constituency": "Belfast East", "name": "Long, N.R. Ms.", "party": "APNI", "votes": 3746, "percentage": 0.122, "change": "-", "changeAmount": 3.7   },
    { "constituency": "Belfast East", "name": "Devenny, D.M. Ms.", "party": "SF", "votes": 1029, "percentage": 0.033, "change": "-", "changeAmount": 0   },
    { "constituency": "Belfast East", "name": "Muldoon, M. Ms.", "party": "SDLP", "votes": 844, "percentage": 0.027, "change": "+", "changeAmount": 0.3   },
    { "constituency": "Belfast East", "name": "Greer, A.J.", "party": "Con", "votes": 434, "percentage": 0.014, "change": "-", "changeAmount": 0.8   },
    { "constituency": "Belfast East", "name": "Bell, J.", "party": "WP", "votes": 179, "percentage": 0.006      },
    { "constituency": "Belfast East", "name": "Gilby, L.J. Ms.", "party": "Vote", "votes": 172, "percentage": 0.006      },
    { "constituency": "Belfast North", "name": "Dodds, N.A.*", "party": "DUP", "votes": 13935, "percentage": 0.456, "change": "+", "changeAmount": 4.8   },
    { "constituency": "Belfast North", "name": "Kelly, G.", "party": "SF", "votes": 8747, "percentage": 0.286, "change": "+", "changeAmount": 3.4   },
    { "constituency": "Belfast North", "name": "Maginness, A.", "party": "SDLP", "votes": 4950, "percentage": 0.162, "change": "-", "changeAmount": 4.8   },
    { "constituency": "Belfast North", "name": "Cobain, F.", "party": "UU", "votes": 2154, "percentage": 0.071, "change": "-", "changeAmount": 4.9   },
    { "constituency": "Belfast North", "name": "Hawkins, M. Ms.", "party": "APNI", "votes": 438, "percentage": 0.014     },
    { "constituency": "Belfast North", "name": "Delaney, M.E. Ms.", "party": "WP", "votes": 165, "percentage": 0.005      },
    { "constituency": "Belfast North", "name": "Gilby, L.J. Ms.", "party": "Vote", "votes": 151, "percentage": 0.005      },
    { "constituency": "Belfast South", "name": "McDonnell, A.", "party": "SDLP", "votes": 10339, "percentage": 0.323, "change": "+", "changeAmount": 1.7   },
    { "constituency": "Belfast South", "name": "Spratt, J.", "party": "DUP", "votes": 9104, "percentage": 0.284 },
    { "constituency": "Belfast South", "name": "McGimpsey, M.H.", "party": "UU", "votes": 7263, "percentage": 0.227, "change": "-", "changeAmount": 22.1   },
    { "constituency": "Belfast South", "name": "Maskey, A.", "party": "SF", "votes": 2882, "percentage": 0.009, "change": "+", "changeAmount": 1.4   },
    { "constituency": "Belfast South", "name": "Rice, G. Ms.", "party": "APNI", "votes": 2012, "percentage": 0.063, "change": "+", "changeAmount": 0.9   },
    { "constituency": "Belfast South", "name": "Gilby, L.J. Ms.", "party": "Vote", "votes": 235, "percentage": 0.007      },
    { "constituency": "Belfast South", "name": "Lynn, P.J.", "party": "WP", "votes": 193, "percentage": 0.006      },
    { "constituency": "Belfast West", "name": "Adams, G.*", "party": "SF", "votes": 24348, "percentage": 0.705, "change": "+", "changeAmount": 4.4   },
    { "constituency": "Belfast West", "name": "Attwood, A.", "party": "SDLP", "votes": 5033, "percentage": 0.146, "change": "-", "changeAmount": 4.4   },
    { "constituency": "Belfast West", "name": "Dodds, D. Ms.", "party": "DUP", "votes": 3652, "percentage": 0.106, "change": "+", "changeAmount": 4.1   },
    { "constituency": "Belfast West", "name": "McGimpsey, C.D.", "party": "UU", "votes": 779, "percentage": 0.023, "change": "-", "changeAmount": 3.9   },
    { "constituency": "Belfast West", "name": "Lowry, J.", "party": "WP", "votes": 432, "percentage": 0.013      },
    { "constituency": "Belfast West", "name": "Gilby, L.J. Ms.", "party": "Vote", "votes": 154, "percentage": 0.004      },
    { "constituency": "Belfast West", "name": "Kennedy, L.", "party": "Ind", "votes": 147, "percentage": 0.004      },
    { "constituency": "Down North", "name": "Hermon, S.E. Ms.*", "party": "UU", "votes": 16268, "percentage": 0.504, "change": "-", "changeAmount": 5.6   },
    { "constituency": "Down North", "name": "Weir, P.J.", "party": "DUP", "votes": 11324, "percentage": 0.351 },
    { "constituency": "Down North", "name": "Alderdice, D.K.", "party": "APNI", "votes": 2451, "percentage": 0.076 },
    { "constituency": "Down North", "name": "Logan, W.P.", "party": "SDLP", "votes": 1009, "percentage": 0.031, "change": "-", "changeAmount": 0.3  },
    { "constituency": "Down North", "name": "Robertson, J.", "party": "Con", "votes": 822, "percentage": 0.025, "change": "+", "changeAmount": 0.4  },
    { "constituency": "Down North", "name": "Carter, C.C.", "party": "Ind", "votes": 211, "percentage": 0.007     },
    { "constituency": "Down North", "name": "McCrory, J. Ms.", "party": "SF", "votes": 205, "percentage": 0.006, "change": "-", "changeAmount": 0.2  },
    { "constituency": "Down South", "name": "McGrady, E.*", "party": "SDLP", "votes": 21557, "percentage": 0.447, "change": "-", "changeAmount": 1.6  },
    { "constituency": "Down South", "name": "Ruane, C.M. Ms.", "party": "SF", "votes": 12417, "percentage": 0.258, "change": "+", "changeAmount": 6  },
    { "constituency": "Down South", "name": "Wells, J.H.", "party": "DUP", "votes": 8815, "percentage": 0.183, "change": "+", "changeAmount": 3.3  },
    { "constituency": "Down South", "name": "Nesbitt, D.", "party": "UU", "votes": 4775, "percentage": 0.099, "change": "-", "changeAmount": 7.7  },
    { "constituency": "Down South", "name": "Crozier, J.", "party": "APNI", "votes": 613, "percentage": 0.013, "change": "-", "changeAmount": 0  },
    { "constituency": "Antrim East", "name": "Wilson, S.", "party": "DUP", "votes": 15766, "percentage": 0.496, "change": "+", "changeAmount": 13.6  },
    { "constituency": "Antrim East", "name": "Beggs, J.R.*", "party": "UU", "votes": 8462, "percentage": 0.266, "change": "-", "changeAmount": 9.8  },
    { "constituency": "Antrim East", "name": "Neeson, S.", "party": "APNI", "votes": 4869, "percentage": 0.153, "change": "+", "changeAmount": 2.9  },
    { "constituency": "Antrim East", "name": "O'Connor, D.G.", "party": "SDLP", "votes": 1695, "percentage": 0.0053, "change": "-", "changeAmount": 2  },
    { "constituency": "Antrim East", "name": "McKeown, J.", "party": "SF", "votes": 828, "percentage": 0.0026, "change": "+", "changeAmount": 0.1  },
    { "constituency": "Antrim East", "name": "Kerr, D.T.", "party": "Vote", "votes": 147, "percentage": 0.005     },
    { "constituency": "Antrim North", "name": "Paisley, I.R.K.*", "party": "DUP", "votes": 25156, "percentage": 0.548, "change": "+", "changeAmount": 4.9  },
    { "constituency": "Antrim North", "name": "McGuigan, P.", "party": "SF", "votes": 7191, "percentage": 0.157, "change": "+", "changeAmount": 5.9   },
    { "constituency": "Antrim North", "name": "McCune, R.J.", "party": "UU", "votes": 6637, "percentage": 0.145, "change": "-", "changeAmount": 6.5   },
    { "constituency": "Antrim North", "name": "Farren, S.N.", "party": "SDLP", "votes": 5585, "percentage": 0.122, "change": "-", "changeAmount": 4.7   },
    { "constituency": "Antrim North", "name": "Dunlop, J.A. Ms.", "party": "APNI", "votes": 1357, "percentage": 0.03, "change": "+", "changeAmount": 0.4   },
    { "constituency": "Antrim South", "name": "McCrea, R.T.W.", "party": "DUP", "votes": 14507, "percentage": 0.382, "change": "+", "changeAmount": 3.4   },
    { "constituency": "Antrim South", "name": "Burnside, D.W.B.*", "party": "UU", "votes": 11059, "percentage": 0.291, "change": "-", "changeAmount": 7.9   },
    { "constituency": "Antrim South", "name": "McClelland, N.P. Ms.", "party": "SDLP", "votes": 4706, "percentage": 0.124, "change": "+", "changeAmount": 0.3   },
    { "constituency": "Antrim South", "name": "Cushinan, H.J.", "party": "SF", "votes": 4407, "percentage": 0.116, "change": "+", "changeAmount": 2.2   },
    { "constituency": "Antrim South", "name": "Ford, D.R.J.", "party": "APNI", "votes": 3278, "percentage": 0.086, "change": "+", "changeAmount": 4.2   },
    { "constituency": "Foyle", "name": "Durkan, J.M.", "party": "SDLP", "votes": 21119, "percentage": 0.463, "change": "-", "changeAmount": 3.9   },
    { "constituency": "Foyle", "name": "McLaughlin, M.", "party": "SF", "votes": 15162, "percentage": 0.332, "change": "+", "changeAmount": 6.7   },
    { "constituency": "Foyle", "name": "Hay, W.", "party": "DUP", "votes": 6557, "percentage": 0.144, "change": "-", "changeAmount": 0.8   },
    { "constituency": "Foyle", "name": "McCann, E.", "party": "SEA", "votes": 1649, "percentage": 0.036      },
    { "constituency": "Foyle", "name": "Storey, E.", "party": "UU", "votes": 1091, "percentage": 0.024, "change": "-", "changeAmount": 4.5   },
    { "constituency": "Foyle", "name": "Reel, B.", "party": "Vote", "votes": 31, "percentage": 0.001      },
    { "constituency": "Strangford", "name": "Robinson, I. Ms.*", "party": "DUP", "votes": 20921, "percentage": 0.565, "change": "+", "changeAmount": 13.6   },
    { "constituency": "Strangford", "name": "McGimpsey, G.", "party": "UU", "votes": 7872, "percentage": 0.213, "change": "-", "changeAmount": 19   },
    { "constituency": "Strangford", "name": "McCarthy, K.", "party": "APNI", "votes": 3332, "percentage": 0.09, "change": "+", "changeAmount": 2.3   },
    { "constituency": "Strangford", "name": "Boyle, J.", "party": "SDLP", "votes": 2496, "percentage": 0.067, "change": "+", "changeAmount": 0.6   },
    { "constituency": "Strangford", "name": "Dick, T.", "party": "Con", "votes": 1462, "percentage": 0.039     },
    { "constituency": "Strangford", "name": "Kennedy, D.", "party": "SF", "votes": 949, "percentage": 0.026, "change": "+", "changeAmount": 0.4   },
    { "constituency": "Lagan Valley", "name": "Donaldson, J.M.*", "party": "DUP", "votes": 23289, "percentage": 0.547, "change": "+", "changeAmount": 41.3   },
    { "constituency": "Lagan Valley", "name": "McCrea, B.", "party": "UU", "votes": 9172, "percentage": 0.215, "change": "-", "changeAmount": 35   },
    { "constituency": "Lagan Valley", "name": "Close, S.A.", "party": "APNI", "votes": 4316, "percentage": 0.101, "change": "-", "changeAmount": 6.5   },
    { "constituency": "Lagan Valley", "name": "Butler, P.", "party": "SF", "votes": 3197, "percentage": 0.075, "change": "+", "changeAmount": 1.6   },
    { "constituency": "Lagan Valley", "name": "Lewsley, P. Ms.", "party": "SDLP", "votes": 2598, "percentage": 0.061, "change": "-", "changeAmount": 1.4   },
    { "constituency": "Upper Bann", "name": "Simpson, D.", "party": "DUP", "votes": 16679, "percentage": 0.375, "change": "+", "changeAmount": 8.1   },
    { "constituency": "Upper Bann", "name": "Trimble, W.D.*", "party": "UU", "votes": 11381, "percentage": 0.256, "change": "-", "changeAmount": 7.9   },
    { "constituency": "Upper Bann", "name": "O'Dowd, J.", "party": "SF", "votes": 9305, "percentage": 0.209, "change": "-", "changeAmount": 0.2   },
    { "constituency": "Upper Bann", "name": "Kelly, D. Ms.", "party": "SDLP", "votes": 5747, "percentage": 0.129, "change": "-", "changeAmount": 2   },
    { "constituency": "Upper Bann", "name": "Castle, A.", "party": "APNI", "votes": 955, "percentage": 0.021     },
    { "constituency": "Upper Bann", "name": "French, T.", "party": "WP", "votes": 355, "percentage": 0.08      },
    { "constituency": "Newry and Armagh", "name": "Murphy, C.T.", "party": "SF", "votes": 20965, "percentage": 0.414, "change": "+", "changeAmount": 10.4    },
    { "constituency": "Newry and Armagh", "name": "Bradley, D.", "party": "SDLP", "votes": 12770, "percentage": 0.252, "change": "-", "changeAmount": 12.2    },
    { "constituency": "Newry and Armagh", "name": "Berry, P.L.", "party": "DUP", "votes": 9311, "percentage": 0.184, "change": "-", "changeAmount": 1    },
    { "constituency": "Newry and Armagh", "name": "Kennedy, D.", "party": "UU", "votes": 7025, "percentage": 0.139, "change": "+", "changeAmount": 1.6    },
    { "constituency": "Newry and Armagh", "name": "Markey, G.", "party": "Ind", "votes": 625, "percentage": 0.012       },
    { "constituency": "Ulster Mid", "name": "McGuinness, M.*", "party": "SF", "votes": 21641, "percentage": 0.476, "change": "-", "changeAmount": 3.4    },
    { "constituency": "Ulster Mid", "name": "McCrea, R.W.I.", "party": "DUP", "votes": 10665, "percentage": 0.235, "change": "-", "changeAmount": 7.7    },
    { "constituency": "Ulster Mid", "name": "McGlone, P.J.", "party": "SDLP", "votes": 7922, "percentage": 0.174, "change": "+", "changeAmount": 0.7    },
    { "constituency": "Ulster Mid", "name": "Armstrong, B.", "party": "UU", "votes": 4853, "percentage": 0.107 },
    { "constituency": "Ulster Mid", "name": "Donnelly, F.", "party": "WP", "votes": 345, "percentage": 0.08       },
    { "constituency": "Tyrone West", "name": "Doherty, P.*", "party": "SF", "votes": 16910, "percentage": 0.389, "change": "-", "changeAmount": 1.9    },
    { "constituency": "Tyrone West", "name": "Deeny, C.K.", "party": "Ind", "votes": 11905, "percentage": 0.274 },
    { "constituency": "Tyrone West", "name": "Buchanan, T.E.", "party": "DUP", "votes": 7742, "percentage": 0.178 },
    { "constituency": "Tyrone West", "name": "McMenamin, E.A.", "party": "SDLP", "votes": 3949, "percentage": 0.091, "change": "-", "changeAmount": 19.6    },
    { "constituency": "Tyrone West", "name": "Hussey, D.R.", "party": "UU", "votes": 2981, "percentage": 0.069, "change": "-", "changeAmount": 23.6    },
    { "constituency": "Fermanagh & South Tyrone", "name": "Gildernew, M. Ms.*", "party": "SF", "votes": 18638, "percentage": 0.382, "change": "+", "changeAmount": 4.1    },
    { "constituency": "Fermanagh & South Tyrone", "name": "Foster, A.I. Ms.", "party": "DUP", "votes": 14056, "percentage": 0.288 },
    { "constituency": "Fermanagh & South Tyrone", "name": "Elliott, T.B.", "party": "UU", "votes": 8869, "percentage": 0.182, "change": "-", "changeAmount": 15.9   },
    { "constituency": "Fermanagh & South Tyrone", "name": "Gallagher, T.", "party": "SDLP", "votes": 7230, "percentage": 0.148, "change": "-", "changeAmount": 3.9   },
    { "constituency": "Londonderry East", "name": "Campbell, G.L.*", "party": "DUP", "votes": 15225, "percentage": 0.429, "change": "+", "changeAmount": 10.7   },
    { "constituency": "Londonderry East", "name": "McClarty, D.", "party": "UU", "votes": 7498, "percentage": 0.211, "change": "-", "changeAmount": 6.3   },
    { "constituency": "Londonderry East", "name": "Dallat, J.J.", "party": "SDLP", "votes": 6077, "percentage": 0.171, "change": "-", "changeAmount": 3.7   },
    { "constituency": "Londonderry East", "name": "Leonard, B.", "party": "SF", "votes": 5709, "percentage": 0.161, "change": "+", "changeAmount": 0.5   },
    { "constituency": "Londonderry East", "name": "Boyle, Y. Ms.", "party": "APNI", "votes": 924, "percentage": 0.026, "change": "-", "changeAmount": 1.5   },
    { "constituency": "Londonderry East", "name": "Samuel, M.H.", "party": "Ind", "votes": 71, "percentage": 0.002  }
]
